AUTHORS.rst
CHANGELOG.rst
LICENSE
MANIFEST.in
README.md
bow.py
setup.py
bagofwords.egg-info/PKG-INFO
bagofwords.egg-info/SOURCES.txt
bagofwords.egg-info/dependency_links.txt
bagofwords.egg-info/entry_points.txt
bagofwords.egg-info/not-zip-safe
bagofwords.egg-info/requires.txt
bagofwords.egg-info/top_level.txt