Metadata-Version: 1.1
Name: bagofwords
Version: 1.0.1
Summary: The main goal this Python module is to provide functions to apply Text Classification.
Home-page: https://github.com/dmiro/bagofwords
Author: David Miro <lite.3engine@gmail.com>
Author-email: lite.3engine@gmail.com
License: The MIT License (MIT)
